nonmouse/__init__.py
nonmouse/__main__.py
nonmouse/args.py
nonmouse/utils.py
nonmouse-2.7.0.dist-info/LICENSE
nonmouse-2.7.0.dist-info/METADATA
nonmouse-2.7.0.dist-info/WHEEL
nonmouse-2.7.0.dist-info/entry_points.txt
nonmouse-2.7.0.dist-info/top_level.txt
nonmouse-2.7.0.dist-info/RECORD
