Metadata-Version: 2.1
Name: nonmouse
Version: 2.7.0
Summary: a webcam-based virtual gesture mouse that is easy to use with hands on the desk
Home-page: https://github.com/takeyamayuki/NonMouse
Author: Yuki TAKEYAMA
Author-email: namiki.takeyama@gmail.com
License: Apache-2.0
Platform: UNKNOWN
Requires-Python: >=3.6
Requires-Dist: absl-py (==1.2.0)
Requires-Dist: altgraph (==0.17.2)
Requires-Dist: attrs (==22.1.0)
Requires-Dist: cycler (==0.11.0)
Requires-Dist: fonttools (==4.36.0)
Requires-Dist: keyboard (==0.13.5)
Requires-Dist: kiwisolver (==1.4.4)
Requires-Dist: macholib (==1.16)
Requires-Dist: matplotlib (==3.5.3)
Requires-Dist: mediapipe (==0.8.10.1)
Requires-Dist: numpy (==1.19.4)
Requires-Dist: opencv-contrib-python (==4.6.0.66)
Requires-Dist: opencv-python (==4.5.3.56)
Requires-Dist: opencv-python-headless (==4.6.0.66)
Requires-Dist: packaging (==21.3)
Requires-Dist: Pillow (==9.2.0)
Requires-Dist: protobuf (==3.20.1)
Requires-Dist: pyinstaller (==4.6)
Requires-Dist: pyinstaller-hooks-contrib (==2022.8)
Requires-Dist: pynput (==1.6.8)
Requires-Dist: pyparsing (==3.0.9)
Requires-Dist: python-dateutil (==2.8.2)
Requires-Dist: six (==1.16.0)
Requires-Dist: pyobjc (==7.3) ; sys_platform == "darwin"
Requires-Dist: pyobjc-core (==7.3) ; sys_platform == "darwin"
Requires-Dist: pyobjc-framework-Accessibility (==7.3) ; sys_platform == "darwin"
Requires-Dist: pyobjc-framework-Accounts (==7.3) ; sys_platform == "darwin"
Requires-Dist: pyobjc-framework-AddressBook (==7.3) ; sys_platform == "darwin"
Requires-Dist: pyobjc-framework-AdServices (==7.3) ; sys_platform == "darwin"
Requires-Dist: pyobjc-framework-AdSupport (==7.3) ; sys_platform == "darwin"
Requires-Dist: pyobjc-framework-AppleScriptKit (==7.3) ; sys_platform == "darwin"
Requires-Dist: pyobjc-framework-AppleScriptObjC (==7.3) ; sys_platform == "darwin"
Requires-Dist: pyobjc-framework-ApplicationServices (==7.3) ; sys_platform == "darwin"
Requires-Dist: pyobjc-framework-AppTrackingTransparency (==7.3) ; sys_platform == "darwin"
Requires-Dist: pyobjc-framework-AuthenticationServices (==7.3) ; sys_platform == "darwin"
Requires-Dist: pyobjc-framework-AutomaticAssessmentConfiguration (==7.3) ; sys_platform == "darwin"
Requires-Dist: pyobjc-framework-Automator (==7.3) ; sys_platform == "darwin"
Requires-Dist: pyobjc-framework-AVFoundation (==7.3) ; sys_platform == "darwin"
Requires-Dist: pyobjc-framework-AVKit (==7.3) ; sys_platform == "darwin"
Requires-Dist: pyobjc-framework-BusinessChat (==7.3) ; sys_platform == "darwin"
Requires-Dist: pyobjc-framework-CalendarStore (==7.3) ; sys_platform == "darwin"
Requires-Dist: pyobjc-framework-CallKit (==7.3) ; sys_platform == "darwin"
Requires-Dist: pyobjc-framework-CFNetwork (==7.3) ; sys_platform == "darwin"
Requires-Dist: pyobjc-framework-ClassKit (==7.3) ; sys_platform == "darwin"
Requires-Dist: pyobjc-framework-CloudKit (==7.3) ; sys_platform == "darwin"
Requires-Dist: pyobjc-framework-Cocoa (==7.3) ; sys_platform == "darwin"
Requires-Dist: pyobjc-framework-Collaboration (==7.3) ; sys_platform == "darwin"
Requires-Dist: pyobjc-framework-ColorSync (==7.3) ; sys_platform == "darwin"
Requires-Dist: pyobjc-framework-Contacts (==7.3) ; sys_platform == "darwin"
Requires-Dist: pyobjc-framework-ContactsUI (==7.3) ; sys_platform == "darwin"
Requires-Dist: pyobjc-framework-CoreAudio (==7.3) ; sys_platform == "darwin"
Requires-Dist: pyobjc-framework-CoreAudioKit (==7.3) ; sys_platform == "darwin"
Requires-Dist: pyobjc-framework-CoreBluetooth (==7.3) ; sys_platform == "darwin"
Requires-Dist: pyobjc-framework-CoreData (==7.3) ; sys_platform == "darwin"
Requires-Dist: pyobjc-framework-CoreHaptics (==7.3) ; sys_platform == "darwin"
Requires-Dist: pyobjc-framework-CoreLocation (==7.3) ; sys_platform == "darwin"
Requires-Dist: pyobjc-framework-CoreMedia (==7.3) ; sys_platform == "darwin"
Requires-Dist: pyobjc-framework-CoreMediaIO (==7.3) ; sys_platform == "darwin"
Requires-Dist: pyobjc-framework-CoreMIDI (==7.3) ; sys_platform == "darwin"
Requires-Dist: pyobjc-framework-CoreML (==7.3) ; sys_platform == "darwin"
Requires-Dist: pyobjc-framework-CoreMotion (==7.3) ; sys_platform == "darwin"
Requires-Dist: pyobjc-framework-CoreServices (==7.3) ; sys_platform == "darwin"
Requires-Dist: pyobjc-framework-CoreSpotlight (==7.3) ; sys_platform == "darwin"
Requires-Dist: pyobjc-framework-CoreText (==7.3) ; sys_platform == "darwin"
Requires-Dist: pyobjc-framework-CoreWLAN (==7.3) ; sys_platform == "darwin"
Requires-Dist: pyobjc-framework-CryptoTokenKit (==7.3) ; sys_platform == "darwin"
Requires-Dist: pyobjc-framework-DeviceCheck (==7.3) ; sys_platform == "darwin"
Requires-Dist: pyobjc-framework-DictionaryServices (==7.3) ; sys_platform == "darwin"
Requires-Dist: pyobjc-framework-DiscRecording (==7.3) ; sys_platform == "darwin"
Requires-Dist: pyobjc-framework-DiscRecordingUI (==7.3) ; sys_platform == "darwin"
Requires-Dist: pyobjc-framework-DiskArbitration (==7.3) ; sys_platform == "darwin"
Requires-Dist: pyobjc-framework-DVDPlayback (==7.3) ; sys_platform == "darwin"
Requires-Dist: pyobjc-framework-EventKit (==7.3) ; sys_platform == "darwin"
Requires-Dist: pyobjc-framework-ExceptionHandling (==7.3) ; sys_platform == "darwin"
Requires-Dist: pyobjc-framework-ExecutionPolicy (==7.3) ; sys_platform == "darwin"
Requires-Dist: pyobjc-framework-ExternalAccessory (==7.3) ; sys_platform == "darwin"
Requires-Dist: pyobjc-framework-FileProvider (==7.3) ; sys_platform == "darwin"
Requires-Dist: pyobjc-framework-FileProviderUI (==7.3) ; sys_platform == "darwin"
Requires-Dist: pyobjc-framework-FinderSync (==7.3) ; sys_platform == "darwin"
Requires-Dist: pyobjc-framework-FSEvents (==7.3) ; sys_platform == "darwin"
Requires-Dist: pyobjc-framework-GameCenter (==7.3) ; sys_platform == "darwin"
Requires-Dist: pyobjc-framework-GameController (==7.3) ; sys_platform == "darwin"
Requires-Dist: pyobjc-framework-GameKit (==7.3) ; sys_platform == "darwin"
Requires-Dist: pyobjc-framework-GameplayKit (==7.3) ; sys_platform == "darwin"
Requires-Dist: pyobjc-framework-ImageCaptureCore (==7.3) ; sys_platform == "darwin"
Requires-Dist: pyobjc-framework-IMServicePlugIn (==7.3) ; sys_platform == "darwin"
Requires-Dist: pyobjc-framework-InputMethodKit (==7.3) ; sys_platform == "darwin"
Requires-Dist: pyobjc-framework-InstallerPlugins (==7.3) ; sys_platform == "darwin"
Requires-Dist: pyobjc-framework-InstantMessage (==7.3) ; sys_platform == "darwin"
Requires-Dist: pyobjc-framework-Intents (==7.3) ; sys_platform == "darwin"
Requires-Dist: pyobjc-framework-IOSurface (==7.3) ; sys_platform == "darwin"
Requires-Dist: pyobjc-framework-iTunesLibrary (==7.3) ; sys_platform == "darwin"
Requires-Dist: pyobjc-framework-KernelManagement (==7.3) ; sys_platform == "darwin"
Requires-Dist: pyobjc-framework-LatentSemanticMapping (==7.3) ; sys_platform == "darwin"
Requires-Dist: pyobjc-framework-LaunchServices (==7.3) ; sys_platform == "darwin"
Requires-Dist: pyobjc-framework-libdispatch (==7.3) ; sys_platform == "darwin"
Requires-Dist: pyobjc-framework-LinkPresentation (==7.3) ; sys_platform == "darwin"
Requires-Dist: pyobjc-framework-LocalAuthentication (==7.3) ; sys_platform == "darwin"
Requires-Dist: pyobjc-framework-MapKit (==7.3) ; sys_platform == "darwin"
Requires-Dist: pyobjc-framework-MediaAccessibility (==7.3) ; sys_platform == "darwin"
Requires-Dist: pyobjc-framework-MediaLibrary (==7.3) ; sys_platform == "darwin"
Requires-Dist: pyobjc-framework-MediaPlayer (==7.3) ; sys_platform == "darwin"
Requires-Dist: pyobjc-framework-MediaToolbox (==7.3) ; sys_platform == "darwin"
Requires-Dist: pyobjc-framework-Metal (==7.3) ; sys_platform == "darwin"
Requires-Dist: pyobjc-framework-MetalKit (==7.3) ; sys_platform == "darwin"
Requires-Dist: pyobjc-framework-MetalPerformanceShaders (==7.3) ; sys_platform == "darwin"
Requires-Dist: pyobjc-framework-MetalPerformanceShadersGraph (==7.3) ; sys_platform == "darwin"
Requires-Dist: pyobjc-framework-MLCompute (==7.3) ; sys_platform == "darwin"
Requires-Dist: pyobjc-framework-ModelIO (==7.3) ; sys_platform == "darwin"
Requires-Dist: pyobjc-framework-MultipeerConnectivity (==7.3) ; sys_platform == "darwin"
Requires-Dist: pyobjc-framework-NaturalLanguage (==7.3) ; sys_platform == "darwin"
Requires-Dist: pyobjc-framework-NetFS (==7.3) ; sys_platform == "darwin"
Requires-Dist: pyobjc-framework-Network (==7.3) ; sys_platform == "darwin"
Requires-Dist: pyobjc-framework-NetworkExtension (==7.3) ; sys_platform == "darwin"
Requires-Dist: pyobjc-framework-NotificationCenter (==7.3) ; sys_platform == "darwin"
Requires-Dist: pyobjc-framework-OpenDirectory (==7.3) ; sys_platform == "darwin"
Requires-Dist: pyobjc-framework-OSAKit (==7.3) ; sys_platform == "darwin"
Requires-Dist: pyobjc-framework-OSLog (==7.3) ; sys_platform == "darwin"
Requires-Dist: pyobjc-framework-PassKit (==7.3) ; sys_platform == "darwin"
Requires-Dist: pyobjc-framework-PencilKit (==7.3) ; sys_platform == "darwin"
Requires-Dist: pyobjc-framework-Photos (==7.3) ; sys_platform == "darwin"
Requires-Dist: pyobjc-framework-PhotosUI (==7.3) ; sys_platform == "darwin"
Requires-Dist: pyobjc-framework-PreferencePanes (==7.3) ; sys_platform == "darwin"
Requires-Dist: pyobjc-framework-PushKit (==7.3) ; sys_platform == "darwin"
Requires-Dist: pyobjc-framework-Quartz (==7.3) ; sys_platform == "darwin"
Requires-Dist: pyobjc-framework-QuickLookThumbnailing (==7.3) ; sys_platform == "darwin"
Requires-Dist: pyobjc-framework-ReplayKit (==7.3) ; sys_platform == "darwin"
Requires-Dist: pyobjc-framework-SafariServices (==7.3) ; sys_platform == "darwin"
Requires-Dist: pyobjc-framework-SceneKit (==7.3) ; sys_platform == "darwin"
Requires-Dist: pyobjc-framework-ScreenSaver (==7.3) ; sys_platform == "darwin"
Requires-Dist: pyobjc-framework-ScreenTime (==7.3) ; sys_platform == "darwin"
Requires-Dist: pyobjc-framework-ScriptingBridge (==7.3) ; sys_platform == "darwin"
Requires-Dist: pyobjc-framework-SearchKit (==7.3) ; sys_platform == "darwin"
Requires-Dist: pyobjc-framework-Security (==7.3) ; sys_platform == "darwin"
Requires-Dist: pyobjc-framework-SecurityFoundation (==7.3) ; sys_platform == "darwin"
Requires-Dist: pyobjc-framework-SecurityInterface (==7.3) ; sys_platform == "darwin"
Requires-Dist: pyobjc-framework-ServiceManagement (==7.3) ; sys_platform == "darwin"
Requires-Dist: pyobjc-framework-Social (==7.3) ; sys_platform == "darwin"
Requires-Dist: pyobjc-framework-SoundAnalysis (==7.3) ; sys_platform == "darwin"
Requires-Dist: pyobjc-framework-Speech (==7.3) ; sys_platform == "darwin"
Requires-Dist: pyobjc-framework-SpriteKit (==7.3) ; sys_platform == "darwin"
Requires-Dist: pyobjc-framework-StoreKit (==7.3) ; sys_platform == "darwin"
Requires-Dist: pyobjc-framework-SyncServices (==7.3) ; sys_platform == "darwin"
Requires-Dist: pyobjc-framework-SystemConfiguration (==7.3) ; sys_platform == "darwin"
Requires-Dist: pyobjc-framework-SystemExtensions (==7.3) ; sys_platform == "darwin"
Requires-Dist: pyobjc-framework-UniformTypeIdentifiers (==7.3) ; sys_platform == "darwin"
Requires-Dist: pyobjc-framework-UserNotifications (==7.3) ; sys_platform == "darwin"
Requires-Dist: pyobjc-framework-UserNotificationsUI (==7.3) ; sys_platform == "darwin"
Requires-Dist: pyobjc-framework-VideoSubscriberAccount (==7.3) ; sys_platform == "darwin"
Requires-Dist: pyobjc-framework-VideoToolbox (==7.3) ; sys_platform == "darwin"
Requires-Dist: pyobjc-framework-Virtualization (==7.3) ; sys_platform == "darwin"
Requires-Dist: pyobjc-framework-Vision (==7.3) ; sys_platform == "darwin"
Requires-Dist: pyobjc-framework-WebKit (==7.3) ; sys_platform == "darwin"
